AUTHORS
ChangeLog
setup.cfg
setup.py
oneview_monasca/__init__.py
oneview_monasca/shell.py
oneview_monasca.egg-info/PKG-INFO
oneview_monasca.egg-info/SOURCES.txt
oneview_monasca.egg-info/dependency_links.txt
oneview_monasca.egg-info/entry_points.txt
oneview_monasca.egg-info/not-zip-safe
oneview_monasca.egg-info/pbr.json
oneview_monasca.egg-info/requires.txt
oneview_monasca.egg-info/top_level.txt
oneview_monasca/application/__init__.py
oneview_monasca/application/coordinator.py
oneview_monasca/application/daemon.py
oneview_monasca/eventbus/__init__.py
oneview_monasca/eventbus/base.py
oneview_monasca/eventbus/node_discovery.py
oneview_monasca/eventbus/priority.py
oneview_monasca/infrastructure/__init__.py
oneview_monasca/infrastructure/commands.py
oneview_monasca/infrastructure/validations.py
oneview_monasca/manager/__init__.py
oneview_monasca/manager/abstract_manager_monasca.py
oneview_monasca/manager/abstract_manager_oneview.py
oneview_monasca/manager/manager_monasca.py
oneview_monasca/manager/manager_oneview.py
oneview_monasca/model/__init__.py
oneview_monasca/model/measurement.py
oneview_monasca/model/status.py
oneview_monasca/publisher/__init__.py
oneview_monasca/publisher/base.py
oneview_monasca/publisher/keeper.py
oneview_monasca/publisher/puller.py
oneview_monasca/publisher/scmb.py
oneview_monasca/shared/__init__.py
oneview_monasca/shared/constants.py
oneview_monasca/shared/exceptions.py
oneview_monasca/shared/log.py
oneview_monasca/shared/parse_command.py
oneview_monasca/shared/section_read.py
oneview_monasca/shared/utils.py